[{
   "SRC":"images/p-1.jpg",
   "Ten":"Smart Watches1",
   "Gia":"$324" 
 },
 {
   "SRC":"images/p-2.jpg",
   "Ten":"Smart Watches2",
   "Gia":"" 
 },
 {
   "SRC":"images/p-3.jpg",
   "Ten":"Smart Watches3",
   "Gia":"" 
 },
 {
   "SRC":"images/p-4.jpg",
   "Ten":"Smart Watches4",
   "Gia":"" 
 },
 {
   "SRC":"images/p-5.jpg",
   "Ten":"Smart Watches5",
   "Gia":"" 
 },
 {
   "SRC":"images/p-6.jpg",
   "Ten":"Smart Watches6",
   "Gia":"" 
 },
 {
   "SRC":"images/p-7.jpg",
   "Ten":"Smart Watches7",
   "Gia":"" 
 },
 {
   "SRC":"images/p-8.jpg",
   "Ten":"Smart Watches8",
   "Gia":"" 
 },
 {
   "SRC":"images/p-9.jpg",
   "Ten":"Smart Watches9",
   "Gia":"" 
 },

 {
   "SRC":"images/p-10.jpg",
   "Ten":"Smart Watches10",
   "Gia":"" 
 },
 {
   "SRC":"images/p-11.jpg",
   "Ten":"Smart Watches11",
   "Gia":"" 
 },
 {
   "SRC":"images/p-12.jpg",
   "Ten":"Smart Watches12",
   "Gia":"" 
 },
 {
   "SRC":"images/p-13.jpg",
   "Ten":"Smart Watches13",
   "Gia":"" 
 },
 {
   "SRC":"images/p-14.jpg",
   "Ten":"Smart Watches14",
   "Gia":"" 
 },
 {
   "SRC":"images/p-15.jpg",
   "Ten":"Smart Watches15",
   "Gia":"" 
 },
 {
   "SRC":"images/p-16.jpg",
   "Ten":"Smart Watches16",
   "Gia":"" 
 },
 {
   "SRC":"images/p-17.jpg",
   "Ten":"Smart Watches17",
   "Gia":"" 
 },
 {
   "SRC":"images/p-18.jpg",
   "Ten":"Smart Watches18",
   "Gia":"" 
 },
 {
   "SRC":"images/p-19.jpg",
   "Ten":"Smart Watches19",
   "Gia":"" 
 },
 {
   "SRC":"images/p-20.jpg",
   "Ten":"Smart Watches20",
   "Gia":"" 
 },
 {
   "SRC":"images/p-21.jpg",
   "Ten":"Smart Watches21",
   "Gia":"" 
 },
 {
   "SRC":"images/p-22.jpg",
   "Ten":"Smart Watches22",
   "Gia":"" 
 },
  {
   "SRC":"images/p-23.jpg",
   "Ten":"Smart Watches23",
   "Gia":"" 
 },
 {
   "SRC":"images/p-24.jpg",
   "Ten":"Smart Watches24",
   "Gia":"" 
 }
 
]
